{
  "cache_invalidated_at": "2026-05-03T20:02:03.340739Z",
  "description": null,
  "archived": false,
  "view_count": 33,
  "collection_position": null,
  "source_card_id": null,
  "table_id": null,
  "can_run_adhoc_query": true,
  "result_metadata": [
    {
      "database_type": "text",
      "semantic_type": "type/Country",
      "lib/deduplicated-name": "country_iso2",
      "lib/original-name": "country_iso2",
      "name": "country_iso2",
      "lib/source": "source/native",
      "lib/source-column-alias": "country_iso2",
      "source": "native",
      "field_ref": [
        "field",
        "country_iso2",
        {
          "base-type": "type/Text"
        }
      ],
      "effective_type": "type/Text",
      "lib/desired-column-alias": "country_iso2",
      "display_name": "country_iso2",
      "fingerprint": {
        "global": {
          "distinct-count": 187,
          "nil%": 0.0
        },
        "type": {
          "type/Text": {
            "percent-json": 0.0,
            "percent-url": 0.0,
            "percent-email": 0.0,
            "percent-state": 0.106951871657754,
            "average-length": 2.0
          }
        }
      },
      "base_type": "type/Text"
    },
    {
      "database_type": "text",
      "semantic_type": "type/Country",
      "lib/deduplicated-name": "country_iso3",
      "lib/original-name": "country_iso3",
      "name": "country_iso3",
      "lib/source": "source/native",
      "lib/source-column-alias": "country_iso3",
      "source": "native",
      "field_ref": [
        "field",
        "country_iso3",
        {
          "base-type": "type/Text"
        }
      ],
      "effective_type": "type/Text",
      "lib/desired-column-alias": "country_iso3",
      "display_name": "country_iso3",
      "fingerprint": {
        "global": {
          "distinct-count": 187,
          "nil%": 0.0
        },
        "type": {
          "type/Text": {
            "percent-json": 0.0,
            "percent-url": 0.0,
            "percent-email": 0.0,
            "percent-state": 0.0,
            "average-length": 3.0
          }
        }
      },
      "base_type": "type/Text"
    },
    {
      "database_type": "text",
      "semantic_type": "type/Country",
      "lib/deduplicated-name": "country_name",
      "lib/original-name": "country_name",
      "name": "country_name",
      "lib/source": "source/native",
      "lib/source-column-alias": "country_name",
      "source": "native",
      "field_ref": [
        "field",
        "country_name",
        {
          "base-type": "type/Text"
        }
      ],
      "effective_type": "type/Text",
      "lib/desired-column-alias": "country_name",
      "display_name": "country_name",
      "fingerprint": {
        "global": {
          "distinct-count": 187,
          "nil%": 0.0
        },
        "type": {
          "type/Text": {
            "percent-json": 0.0,
            "percent-url": 0.0,
            "percent-email": 0.0,
            "percent-state": 0.005347593582887701,
            "average-length": 9.133689839572192
          }
        }
      },
      "base_type": "type/Text"
    },
    {
      "database_type": "int4",
      "semantic_type": null,
      "lib/deduplicated-name": "latest_year",
      "lib/original-name": "latest_year",
      "name": "latest_year",
      "lib/source": "source/native",
      "lib/source-column-alias": "latest_year",
      "source": "native",
      "field_ref": [
        "field",
        "latest_year",
        {
          "base-type": "type/Integer"
        }
      ],
      "effective_type": "type/Integer",
      "lib/desired-column-alias": "latest_year",
      "display_name": "latest_year",
      "fingerprint": {
        "global": {
          "distinct-count": 1,
          "nil%": 0.0
        },
        "type": {
          "type/Number": {
            "min": 2020.0,
            "q1": 2020.0,
            "q3": 2020.0,
            "max": 2020.0,
            "sd": 0.0,
            "avg": 2020.0
          }
        }
      },
      "base_type": "type/Integer"
    },
    {
      "database_type": "float8",
      "semantic_type": null,
      "lib/deduplicated-name": "co2_per_capita_t",
      "lib/original-name": "co2_per_capita_t",
      "name": "co2_per_capita_t",
      "lib/source": "source/native",
      "lib/source-column-alias": "co2_per_capita_t",
      "source": "native",
      "field_ref": [
        "field",
        "co2_per_capita_t",
        {
          "base-type": "type/Float"
        }
      ],
      "effective_type": "type/Float",
      "lib/desired-column-alias": "co2_per_capita_t",
      "display_name": "co2_per_capita_t",
      "fingerprint": {
        "global": {
          "distinct-count": 186,
          "nil%": 0.0
        },
        "type": {
          "type/Number": {
            "min": 0.0,
            "q1": 0.6560755650217434,
            "q3": 5.0796720587790105,
            "max": 71.7401079136691,
            "sd": 7.353158690534431,
            "avg": 4.422506117851124
          }
        }
      },
      "base_type": "type/Float"
    },
    {
      "database_type": "float8",
      "semantic_type": null,
      "lib/deduplicated-name": "pm25_annual_satellite_ugm3",
      "lib/original-name": "pm25_annual_satellite_ugm3",
      "name": "pm25_annual_satellite_ugm3",
      "lib/source": "source/native",
      "lib/source-column-alias": "pm25_annual_satellite_ugm3",
      "source": "native",
      "field_ref": [
        "field",
        "pm25_annual_satellite_ugm3",
        {
          "base-type": "type/Float"
        }
      ],
      "effective_type": "type/Float",
      "lib/desired-column-alias": "pm25_annual_satellite_ugm3",
      "display_name": "pm25_annual_satellite_ugm3",
      "fingerprint": {
        "global": {
          "distinct-count": 187,
          "nil%": 0.0
        },
        "type": {
          "type/Number": {
            "min": 4.89518090216668,
            "q1": 13.125790965574463,
            "q3": 30.428264580946863,
            "max": 85.1223455605238,
            "sd": 15.122301401773122,
            "avg": 24.23077860280669
          }
        }
      },
      "base_type": "type/Float"
    },
    {
      "database_type": "float8",
      "semantic_type": null,
      "lib/deduplicated-name": "ratio_co2_pm25",
      "lib/original-name": "ratio_co2_pm25",
      "name": "ratio_co2_pm25",
      "lib/source": "source/native",
      "lib/source-column-alias": "ratio_co2_pm25",
      "source": "native",
      "field_ref": [
        "field",
        "ratio_co2_pm25",
        {
          "base-type": "type/Float"
        }
      ],
      "effective_type": "type/Float",
      "lib/desired-column-alias": "ratio_co2_pm25",
      "display_name": "ratio_co2_pm25",
      "fingerprint": {
        "global": {
          "distinct-count": 186,
          "nil%": 0.0
        },
        "type": {
          "type/Number": {
            "min": 0.0,
            "q1": 0.025403884543330455,
            "q3": 0.3565979665921859,
            "max": 9.790249604231166,
            "sd": 0.8152174831532704,
            "avg": 0.32438639688869797
          }
        }
      },
      "base_type": "type/Float"
    }
  ],
  "embedding_type": null,
  "creator": {
    "email": "admin@climate.local",
    "first_name": "Climate",
    "is_data_analyst": false,
    "last_login": "2026-05-03T20:07:39.593735Z",
    "is_qbnewb": false,
    "is_superuser": true,
    "id": 1,
    "last_name": "Admin",
    "tenant_id": null,
    "date_joined": "2026-05-02T12:51:26.571189Z",
    "common_name": "Climate Admin"
  },
  "initially_published_at": null,
  "can_write": true,
  "card_schema": 23,
  "database_id": 2,
  "enable_embedding": false,
  "collection_id": 5,
  "query_type": "native",
  "name": "Choropleth: CO2/PM2.5 ratio",
  "last_query_start": "2026-05-03T20:02:27.553421Z",
  "is_remote_synced": false,
  "dashboard_count": 1,
  "document_id": null,
  "last_used_at": "2026-05-03T20:02:27.570188Z",
  "dashboard": null,
  "type": "question",
  "dimensions": null,
  "average_query_time": 42.93939393939394,
  "creator_id": 1,
  "can_restore": false,
  "moderation_reviews": [],
  "updated_at": "2026-05-03T20:02:03.339901Z",
  "made_public_by_id": null,
  "embedding_params": null,
  "cache_ttl": null,
  "dataset_query": {
    "lib/type": "mbql/query",
    "database": 2,
    "stages": [
      {
        "lib/type": "mbql.stage/native",
        "template-tags": {
          "year": {
            "display-name": "Year",
            "type": "number",
            "id": "year-tag",
            "name": "year",
            "required": false
          }
        },
        "native": "WITH ranked AS (\n  SELECT m.country_iso3, m.country_name, m.year,\n         m.co2_per_capita_t, m.pm25_annual_satellite_ugm3,\n         ROW_NUMBER() OVER (\n           PARTITION BY m.country_iso3 ORDER BY m.year DESC\n         ) AS rn\n  FROM marts.country_year_environment m\n  WHERE m.co2_per_capita_t IS NOT NULL\n    AND m.pm25_annual_satellite_ugm3 IS NOT NULL\n    AND m.pm25_annual_satellite_ugm3 > 0\n    [[ AND m.year = {{year}} ]]\n)\nSELECT c.iso2 AS country_iso2,\n       r.country_iso3, r.country_name,\n       r.year AS latest_year,\n       r.co2_per_capita_t, r.pm25_annual_satellite_ugm3,\n       r.co2_per_capita_t / r.pm25_annual_satellite_ugm3 AS ratio_co2_pm25\nFROM ranked r\nJOIN seeds.country_iso_codes c\n  ON c.iso3 = r.country_iso3\nWHERE r.rn = 1\nORDER BY country_iso2"
      }
    ]
  },
  "dimension_mappings": null,
  "id": 40,
  "legacy_query": null,
  "parameter_mappings": [],
  "can_manage_db": true,
  "display": "map",
  "archived_directly": false,
  "entity_id": "1c3mPPWvEnR0pb5eeJTeJ",
  "param_fields": {},
  "collection_preview": true,
  "last-edit-info": {
    "id": 1,
    "email": "admin@climate.local",
    "first_name": "Climate",
    "last_name": "Admin",
    "timestamp": "2026-05-03T20:02:03.358233Z"
  },
  "visualization_settings": {
    "map.type": "region",
    "map.region": "world_countries",
    "map.dimension": [
      "field",
      "country_iso2",
      null
    ],
    "map.metric": "ratio_co2_pm25",
    "map.colors": [
      "rgb(252, 218, 218)",
      "rgb(246, 169, 169)",
      "rgb(241, 120, 120)",
      "rgb(236, 71, 71)",
      "hsl(0, 82.9%, 43.2%)"
    ]
  },
  "collection": {
    "authority_level": null,
    "description": "Pollution vs development tiles for the climate-and-development project.",
    "archived": false,
    "workspace_id": null,
    "slug": "climate_vs_development",
    "archive_operation_id": null,
    "name": "Climate vs Development",
    "is_remote_synced": false,
    "personal_owner_id": null,
    "type": null,
    "is_sample": false,
    "id": 5,
    "archived_directly": null,
    "entity_id": "Vq2bFOgd0pcU2BpEWINpX",
    "location": "/",
    "namespace": null,
    "is_personal": false,
    "created_at": "2026-05-02T14:19:42.903367Z"
  },
  "metabase_version": "v0.60.3.3 (c734864)",
  "parameters": [
    {
      "id": "year-tag",
      "type": "number/=",
      "target": [
        "variable",
        [
          "template-tag",
          "year"
        ]
      ],
      "name": "Year",
      "slug": "year",
      "required": false,
      "isMultiSelect": false
    }
  ],
  "dashboard_id": null,
  "created_at": "2026-05-02T14:19:42.992778Z",
  "parameter_usage_count": 0,
  "public_uuid": null,
  "can_delete": false
}
