{
  "cache_invalidated_at": "2026-05-03T20:02:03.489262Z",
  "description": null,
  "archived": false,
  "view_count": 28,
  "collection_position": null,
  "source_card_id": null,
  "table_id": null,
  "can_run_adhoc_query": true,
  "result_metadata": [
    {
      "database_type": "text",
      "semantic_type": "type/Country",
      "lib/deduplicated-name": "country_iso2",
      "lib/original-name": "country_iso2",
      "name": "country_iso2",
      "lib/source": "source/native",
      "lib/source-column-alias": "country_iso2",
      "source": "native",
      "field_ref": [
        "field",
        "country_iso2",
        {
          "base-type": "type/Text"
        }
      ],
      "effective_type": "type/Text",
      "lib/desired-column-alias": "country_iso2",
      "display_name": "country_iso2",
      "fingerprint": {
        "global": {
          "distinct-count": 6,
          "nil%": 0.0
        },
        "type": {
          "type/Text": {
            "percent-json": 0.0,
            "percent-url": 0.0,
            "percent-email": 0.0,
            "percent-state": 0.3333333333333333,
            "average-length": 2.0
          }
        }
      },
      "base_type": "type/Text"
    },
    {
      "database_type": "text",
      "semantic_type": "type/Country",
      "lib/deduplicated-name": "country_name",
      "lib/original-name": "country_name",
      "name": "country_name",
      "lib/source": "source/native",
      "lib/source-column-alias": "country_name",
      "source": "native",
      "field_ref": [
        "field",
        "country_name",
        {
          "base-type": "type/Text"
        }
      ],
      "effective_type": "type/Text",
      "lib/desired-column-alias": "country_name",
      "display_name": "country_name",
      "fingerprint": {
        "global": {
          "distinct-count": 6,
          "nil%": 0.0
        },
        "type": {
          "type/Text": {
            "percent-json": 0.0,
            "percent-url": 0.0,
            "percent-email": 0.0,
            "percent-state": 0.0,
            "average-length": 8.0
          }
        }
      },
      "base_type": "type/Text"
    },
    {
      "database_type": "int4",
      "semantic_type": null,
      "lib/deduplicated-name": "year",
      "lib/original-name": "year",
      "name": "year",
      "lib/source": "source/native",
      "lib/source-column-alias": "year",
      "source": "native",
      "field_ref": [
        "field",
        "year",
        {
          "base-type": "type/Integer"
        }
      ],
      "effective_type": "type/Integer",
      "lib/desired-column-alias": "year",
      "display_name": "year",
      "fingerprint": {
        "global": {
          "distinct-count": 1,
          "nil%": 0.0
        },
        "type": {
          "type/Number": {
            "min": 2020.0,
            "q1": 2020.0,
            "q3": 2020.0,
            "max": 2020.0,
            "sd": 0.0,
            "avg": 2020.0
          }
        }
      },
      "base_type": "type/Integer"
    },
    {
      "database_type": "float8",
      "semantic_type": null,
      "lib/deduplicated-name": "gdp_per_capita_usd",
      "lib/original-name": "gdp_per_capita_usd",
      "name": "gdp_per_capita_usd",
      "lib/source": "source/native",
      "lib/source-column-alias": "gdp_per_capita_usd",
      "source": "native",
      "field_ref": [
        "field",
        "gdp_per_capita_usd",
        {
          "base-type": "type/Float"
        }
      ],
      "effective_type": "type/Float",
      "lib/desired-column-alias": "gdp_per_capita_usd",
      "display_name": "gdp_per_capita_usd",
      "fingerprint": {
        "global": {
          "distinct-count": 6,
          "nil%": 0.0
        },
        "type": {
          "type/Number": {
            "min": 1907.04251637669,
            "q1": 5580.60383075189,
            "q3": 47394.8734504469,
            "max": 63515.9491807833,
            "sd": 25840.071725323425,
            "avg": 22977.867254619894
          }
        }
      },
      "base_type": "type/Float"
    },
    {
      "database_type": "float8",
      "semantic_type": null,
      "lib/deduplicated-name": "pm25_annual_satellite_ugm3",
      "lib/original-name": "pm25_annual_satellite_ugm3",
      "name": "pm25_annual_satellite_ugm3",
      "lib/source": "source/native",
      "lib/source-column-alias": "pm25_annual_satellite_ugm3",
      "source": "native",
      "field_ref": [
        "field",
        "pm25_annual_satellite_ugm3",
        {
          "base-type": "type/Float"
        }
      ],
      "effective_type": "type/Float",
      "lib/desired-column-alias": "pm25_annual_satellite_ugm3",
      "display_name": "pm25_annual_satellite_ugm3",
      "fingerprint": {
        "global": {
          "distinct-count": 6,
          "nil%": 0.0
        },
        "type": {
          "type/Number": {
            "min": 7.81485752365112,
            "q1": 10.2876894329414,
            "q3": 34.8105237153218,
            "max": 48.3948115195574,
            "sd": 15.75159237448552,
            "avg": 23.342215909694037
          }
        }
      },
      "base_type": "type/Float"
    },
    {
      "database_type": "float8",
      "semantic_type": null,
      "lib/deduplicated-name": "population_total",
      "lib/original-name": "population_total",
      "name": "population_total",
      "lib/source": "source/native",
      "lib/source-column-alias": "population_total",
      "source": "native",
      "field_ref": [
        "field",
        "population_total",
        {
          "base-type": "type/Float"
        }
      ],
      "effective_type": "type/Float",
      "lib/desired-column-alias": "population_total",
      "display_name": "population_total",
      "fingerprint": {
        "global": {
          "distinct-count": 6,
          "nil%": 0.0
        },
        "type": {
          "type/Number": {
            "min": 60562381.0,
            "q1": 83160871.0,
            "q3": 1402617695.0,
            "max": 1411100000.0,
            "sd": 655821592.8280702,
            "avg": 569302953.5
          }
        }
      },
      "base_type": "type/Float"
    },
    {
      "database_type": "float8",
      "semantic_type": null,
      "lib/deduplicated-name": "log_population",
      "lib/original-name": "log_population",
      "name": "log_population",
      "lib/source": "source/native",
      "lib/source-column-alias": "log_population",
      "source": "native",
      "field_ref": [
        "field",
        "log_population",
        {
          "base-type": "type/Float"
        }
      ],
      "effective_type": "type/Float",
      "lib/desired-column-alias": "log_population",
      "display_name": "log_population",
      "fingerprint": {
        "global": {
          "distinct-count": 6,
          "nil%": 0.0
        },
        "type": {
          "type/Number": {
            "min": 17.91918448270105,
            "q1": 18.23628749468471,
            "q3": 21.061606109843773,
            "max": 21.06763537902799,
            "sd": 1.3916262598795481,
            "avg": 19.4270333992021
          }
        }
      },
      "base_type": "type/Float"
    }
  ],
  "embedding_type": null,
  "creator": {
    "email": "admin@climate.local",
    "first_name": "Climate",
    "is_data_analyst": false,
    "last_login": "2026-05-03T20:07:39.593735Z",
    "is_qbnewb": false,
    "is_superuser": true,
    "id": 1,
    "last_name": "Admin",
    "tenant_id": null,
    "date_joined": "2026-05-02T12:51:26.571189Z",
    "common_name": "Climate Admin"
  },
  "initially_published_at": null,
  "can_write": true,
  "card_schema": 23,
  "database_id": 2,
  "enable_embedding": false,
  "collection_id": 5,
  "query_type": "native",
  "name": "GDP vs PM2.5 (latest year, bubble = log population)",
  "last_query_start": "2026-05-03T20:02:27.552788Z",
  "is_remote_synced": false,
  "dashboard_count": 1,
  "document_id": null,
  "last_used_at": "2026-05-03T20:02:27.570188Z",
  "dashboard": null,
  "type": "question",
  "dimensions": null,
  "average_query_time": 34.535714285714285,
  "creator_id": 1,
  "can_restore": false,
  "moderation_reviews": [],
  "updated_at": "2026-05-03T20:02:03.4868Z",
  "made_public_by_id": null,
  "embedding_params": null,
  "cache_ttl": null,
  "dataset_query": {
    "lib/type": "mbql/query",
    "database": 2,
    "stages": [
      {
        "lib/type": "mbql.stage/native",
        "native": "WITH ranked AS (\n  SELECT m.country_iso3, m.country_name, m.year,\n         m.gdp_per_capita_usd, m.pm25_annual_satellite_ugm3, m.population_total,\n         ROW_NUMBER() OVER (\n           PARTITION BY m.country_iso3 ORDER BY m.year DESC\n         ) AS rn\n  FROM marts.country_year_environment m\n  WHERE m.gdp_per_capita_usd IS NOT NULL\n    AND m.pm25_annual_satellite_ugm3 IS NOT NULL\n    AND m.population_total IS NOT NULL\n)\nSELECT c.iso2 AS country_iso2,\n       r.country_name, r.year,\n       r.gdp_per_capita_usd, r.pm25_annual_satellite_ugm3,\n       r.population_total,\n       LN(r.population_total) AS log_population\nFROM ranked r\nJOIN seeds.country_iso_codes c\n  ON c.iso3 = r.country_iso3\nWHERE r.rn = 1\n  AND c.iso2 IN ('US','DE','CN','MX','IN','ZA')\n  [[ AND c.iso2 IN ({{country_iso2}}) ]]\nORDER BY country_iso2",
        "template-tags": {
          "country_iso2": {
            "display-name": "Countries (ISO2)",
            "type": "text",
            "id": "country-iso2-tag",
            "name": "country_iso2",
            "required": false
          }
        }
      }
    ]
  },
  "dimension_mappings": null,
  "id": 42,
  "legacy_query": null,
  "parameter_mappings": [],
  "can_manage_db": true,
  "display": "scatter",
  "archived_directly": false,
  "entity_id": "6o1f1mVKQ5F6ZJU7tI0DS",
  "param_fields": {},
  "collection_preview": true,
  "last-edit-info": {
    "id": 1,
    "email": "admin@climate.local",
    "first_name": "Climate",
    "last_name": "Admin",
    "timestamp": "2026-05-03T20:02:03.523197Z"
  },
  "visualization_settings": {
    "graph.y_axis.title_text": "PM2.5 satellite annual (µg/m³)",
    "graph.show_values": true,
    "scatter.bubble": "log_population",
    "graph.x_axis.title_text": "GDP per capita (USD, log)",
    "graph.label_value_frequency": "all",
    "graph.metrics": [
      "pm25_annual_satellite_ugm3"
    ],
    "graph.tooltip_columns": [
      "[\"name\",\"country_name\"]",
      "[\"name\",\"population_total\"]",
      "[\"name\",\"year\"]"
    ],
    "graph.x_axis.scale": "log",
    "graph.dimensions": [
      "gdp_per_capita_usd",
      "country_iso2"
    ]
  },
  "collection": {
    "authority_level": null,
    "description": "Pollution vs development tiles for the climate-and-development project.",
    "archived": false,
    "workspace_id": null,
    "slug": "climate_vs_development",
    "archive_operation_id": null,
    "name": "Climate vs Development",
    "is_remote_synced": false,
    "personal_owner_id": null,
    "type": null,
    "is_sample": false,
    "id": 5,
    "archived_directly": null,
    "entity_id": "Vq2bFOgd0pcU2BpEWINpX",
    "location": "/",
    "namespace": null,
    "is_personal": false,
    "created_at": "2026-05-02T14:19:42.903367Z"
  },
  "metabase_version": "v0.60.3.3 (c734864)",
  "parameters": [
    {
      "id": "country-iso2-tag",
      "type": "category",
      "target": [
        "variable",
        [
          "template-tag",
          "country_iso2"
        ]
      ],
      "name": "Countries (ISO2)",
      "slug": "country_iso2",
      "required": false,
      "isMultiSelect": true
    }
  ],
  "dashboard_id": null,
  "created_at": "2026-05-02T14:19:43.174122Z",
  "parameter_usage_count": 0,
  "public_uuid": null,
  "can_delete": false
}
